{
  "model_id": "MODEL-HD1003-001",
  "source_spec_id": "CNTR-15000TEU-001",
  "source_project_name": "HD1003",
  "title": "HD1003 Container 통합 기준 모델",
  "discipline": "선체/의장 통합",
  "model_profile": {
    "basic_info": {
      "ship_type": "CONTAINER"
    },
    "principal_dimensions": {
      "loa_m": 366.0,
      "breadth_m": 51.0,
      "draft_m": 15.0
    },
    "machinery": {
      "main_engine": "WinGD"
    },
    "cargo_system": {
      "capacity_teu": 15000
    }
  },
  "model_hierarchy": [
    {
      "path": "PROJECT/HD1003",
      "node_code": "HD1003",
      "name": "HD1003",
      "type": "Project",
      "design_structure": "프로젝트",
      "model_type": "프로젝트",
      "spec_basis": "15000TEU Container"
    },
    {
      "path": "PROJECT/HD1003/HULL",
      "node_code": "HULL",
      "name": "선체",
      "type": "Discipline",
      "design_structure": "선체",
      "model_type": "설계구조"
    },
    {
      "path": "PROJECT/HD1003/HULL/SHELL-PLATING",
      "node_code": "SHELL-PLATING",
      "name": "외판 구조",
      "type": "Assembly",
      "design_structure": "선체",
      "model_type": "플레이트 그룹"
    },
    {
      "path": "PROJECT/HD1003/HULL/SHELL-PLATING/SIDE-SHELL/PLATE-SS-001",
      "node_code": "PLATE-SS-001",
      "name": "현측 외판 001",
      "type": "Part",
      "design_structure": "선체",
      "model_type": "플레이트",
      "spec_basis": "LOA/Breadth 반영",
      "reuse_hint_fields": [
        "principal_dimensions.loa_m",
        "principal_dimensions.breadth_m"
      ]
    },
    {
      "path": "PROJECT/HD1003/HULL/DECK-STRUCTURE",
      "node_code": "DECK-STRUCTURE",
      "name": "갑판 구조",
      "type": "Assembly",
      "design_structure": "선체",
      "model_type": "갑판 구조"
    },
    {
      "path": "PROJECT/HD1003/HULL/DECK-STRUCTURE/HATCH-COAMING",
      "node_code": "HATCH-COAMING",
      "name": "해치 코밍",
      "type": "Assembly",
      "design_structure": "선체",
      "model_type": "보강 구조"
    },
    {
      "path": "PROJECT/HD1003/HULL/DECK-STRUCTURE/HATCH-COAMING/STIFFENER-HC-001",
      "node_code": "STIFFENER-HC-001",
      "name": "해치 코밍 보강재 001",
      "type": "Part",
      "design_structure": "선체",
      "model_type": "스티프너",
      "spec_basis": "TEU 용량 반영",
      "reuse_hint_fields": [
        "cargo_system.capacity_teu"
      ]
    },
    {
      "path": "PROJECT/HD1003/OUTFIT-STEEL",
      "node_code": "OUTFIT-STEEL",
      "name": "의장-철의",
      "type": "Discipline",
      "design_structure": "의장-철의",
      "model_type": "설계구조"
    },
    {
      "path": "PROJECT/HD1003/OUTFIT-STEEL/LASHING-SUPPORT",
      "node_code": "LASHING-SUPPORT",
      "name": "래싱 지지구조",
      "type": "Assembly",
      "design_structure": "의장-철의",
      "model_type": "서포트 구조",
      "spec_basis": "TEU 용량 반영",
      "reuse_hint_fields": [
        "cargo_system.capacity_teu"
      ]
    },
    {
      "path": "PROJECT/HD1003/OUTFIT-STEEL/LASHING-SUPPORT/SUPPORT-LS-001",
      "node_code": "SUPPORT-LS-001",
      "name": "래싱 지지대 001",
      "type": "Part",
      "design_structure": "의장-철의",
      "model_type": "서포트",
      "spec_basis": "TEU 용량 반영"
    },
    {
      "path": "PROJECT/HD1003/OUTFIT-PIPING",
      "node_code": "OUTFIT-PIPING",
      "name": "의장-배관",
      "type": "Discipline",
      "design_structure": "의장-배관",
      "model_type": "설계구조"
    },
    {
      "path": "PROJECT/HD1003/OUTFIT-PIPING/BALLAST-LINE",
      "node_code": "BALLAST-LINE",
      "name": "발라스트 라인",
      "type": "Assembly",
      "design_structure": "의장-배관",
      "model_type": "배관 묶음",
      "spec_basis": "선형 반영"
    },
    {
      "path": "PROJECT/HD1003/OUTFIT-PIPING/BALLAST-LINE/PIPE-BL-001",
      "node_code": "PIPE-BL-001",
      "name": "발라스트 파이프 001",
      "type": "Part",
      "design_structure": "의장-배관",
      "model_type": "파이프",
      "spec_basis": "선형 반영"
    },
    {
      "path": "PROJECT/HD1003/OUTFIT-ELECTRIC",
      "node_code": "OUTFIT-ELECTRIC",
      "name": "의장-전장",
      "type": "Discipline",
      "design_structure": "의장-전장",
      "model_type": "설계구조"
    },
    {
      "path": "PROJECT/HD1003/OUTFIT-ELECTRIC/DECK-LIGHTING",
      "node_code": "DECK-LIGHTING",
      "name": "갑판 조명",
      "type": "Assembly",
      "design_structure": "의장-전장",
      "model_type": "전장 묶음"
    },
    {
      "path": "PROJECT/HD1003/OUTFIT-ELECTRIC/DECK-LIGHTING/CABLE-TRAY-001",
      "node_code": "CABLE-TRAY-001",
      "name": "갑판 케이블 트레이 001",
      "type": "Part",
      "design_structure": "의장-전장",
      "model_type": "케이블트레이",
      "spec_basis": "갑판 배치 반영"
    },
    {
      "path": "PROJECT/HD1003/OUTFIT-MACHINERY",
      "node_code": "OUTFIT-MACHINERY",
      "name": "의장-기계",
      "type": "Discipline",
      "design_structure": "의장-기계",
      "model_type": "설계구조"
    },
    {
      "path": "PROJECT/HD1003/OUTFIT-MACHINERY/MAIN-PROPULSION/MAIN-ENGINE",
      "node_code": "MAIN-ENGINE",
      "name": "메인 엔진 기자재",
      "type": "Assembly",
      "design_structure": "의장-기계",
      "model_type": "메인엔진",
      "spec_basis": "메인 엔진 기자재 반영",
      "reuse_hint_fields": [
        "machinery.main_engine"
      ]
    }
  ],
  "model_notes": [
    "컨테이너선 기준 모델 역시 block division 이전 설계구조만을 표현합니다.",
    "선체, 래싱 지지구조, 전장 구조를 중심으로 재활용 판단을 수행합니다."
  ]
}
